cogn/__init__.py
cogn-1.0.dist-info/METADATA
cogn-1.0.dist-info/WHEEL
cogn-1.0.dist-info/top_level.txt
cogn-1.0.dist-info/RECORD
