Metadata-Version: 2.1
Name: cogn
Version: 1.0
Summary: package with cognitive codes
Author: Black_shark
